package_sum_numbers/__init__.py
package_sum_numbers/sum.py
package_sum_numbers-0.0.1.dist-info/METADATA
package_sum_numbers-0.0.1.dist-info/WHEEL
package_sum_numbers-0.0.1.dist-info/licenses/LICENSE.txt
package_sum_numbers-0.0.1.dist-info/RECORD
